<?xml version="1.0" encoding="UTF-8"?><database>
    <element label="main" max_length="40" name="x_882237_gam_main" sizeclass="0" type="collection">
        <element attributes="encode_utf8=false" label="LAN ID" max_length="32" name="lan_id" reference="cmdb_ci_lb_ace" type="reference"/>
        <element attributes="edge_encryption_enabled=true" default="javascript:global.getNextObjNumberPadded();" label="Number" max_length="40" name="number" type="string"/>
        <element default="javascript:current.getTableName();" label="Class" max_length="80" name="sys_class_name" type="sys_class_name"/>
        <index name="index">
            <element name="lan_id"/>
        </index>
        <index name="index2">
            <element name="sys_class_name"/>
        </index>
    </element>
</database>
